taodata/__init__.py
taodata/td_data.py
taodata/api/__init__.py
taodata/util/__init__.py
taodata/util/auth.py
taodata/util/client.py
taodata/util/cons.py
taodata/util/dsl.py
test/__init__.py
test/auth_test.py
test/client_test.py
taodata-0.1.13.dist-info/LICENSE
taodata-0.1.13.dist-info/METADATA
taodata-0.1.13.dist-info/WHEEL
taodata-0.1.13.dist-info/top_level.txt
taodata-0.1.13.dist-info/RECORD
