Metadata-Version: 2.1
Name: taodata
Version: 0.1.13
Summary: todo
Home-page: https://taodata.pro
Author: Daniel Qian
Author-email: 909263817@qq.com
License: MIT
Keywords: todo
Platform: UNKNOWN
Classifier: Programming Language :: Python :: 3
Classifier: License :: OSI Approved :: MIT License
Classifier: Operating System :: OS Independent
License-File: LICENSE
Requires-Dist: requests
Requires-Dist: pandas
